tosspay/__about__.py
tosspay/__init__.py
tosspay/tosspay_json.py
tosspay-1.0.1.dist-info/METADATA
tosspay-1.0.1.dist-info/WHEEL
tosspay-1.0.1.dist-info/licenses/LICENSE
tosspay-1.0.1.dist-info/RECORD
