Metadata-Version: 2.3
Name: tosspay
Version: 1.0.1
Summary: 사업자 등록증 없이 결제 시스템을 만들수있는 라이브러리
Project-URL: Documentation, https://github.com/tosspay-lib/tosspay-py/docs
Project-URL: Issues, https://github.com/tosspay-lib/tosspay-py/issues
Project-URL: Source, https://github.com/tosspay-lib/tosspay-py
Author-email: 5-23 <yhanbyeol6@gmail.com>
License-Expression: Apache-2.0
License-File: LICENSE
Classifier: Development Status :: 4 - Beta
Classifier: Programming Language :: Python
Classifier: Programming Language :: Python :: 3.8
Classifier: Programming Language :: Python :: 3.9
Classifier: Programming Language :: Python :: 3.10
Classifier: Programming Language :: Python :: 3.11
Classifier: Programming Language :: Python :: 3.12
Classifier: Programming Language :: Python :: Implementation :: CPython
Classifier: Programming Language :: Python :: Implementation :: PyPy
Requires-Python: >=3.8
Requires-Dist: requests
